aiidalab_qe_wannier90/__init__.py
aiidalab_qe_wannier90/model.py
aiidalab_qe_wannier90/resources.py
aiidalab_qe_wannier90/setting.py
aiidalab_qe_wannier90/utils.py
aiidalab_qe_wannier90/wannier90.py
aiidalab_qe_wannier90/wannier90_workchain.py
aiidalab_qe_wannier90/workchain.py
aiidalab_qe_wannier90/result/__init__.py
aiidalab_qe_wannier90/result/model.py
aiidalab_qe_wannier90/result/result.py
aiidalab_qe_wannier90-0.1.6.dist-info/entry_points.txt
aiidalab_qe_wannier90-0.1.6.dist-info/licenses/LICENSE
aiidalab_qe_wannier90-0.1.6.dist-info/WHEEL
aiidalab_qe_wannier90-0.1.6.dist-info/METADATA
aiidalab_qe_wannier90-0.1.6.dist-info/RECORD
